snakesays/__init__.py
snakesays/__main__.py
snakesays/cli.py
snakesays/snake.py
snakesays-1.2.5.dist-info/entry_points.txt
snakesays-1.2.5.dist-info/METADATA
snakesays-1.2.5.dist-info/WHEEL
snakesays-1.2.5.dist-info/RECORD
